lytorch/__init__.py
lytorch/test.py
lytorch/nn/__init__.py
lytorch/nn/test.py
lytorch-0.0.4.dist-info/LICENSE
lytorch-0.0.4.dist-info/METADATA
lytorch-0.0.4.dist-info/WHEEL
lytorch-0.0.4.dist-info/top_level.txt
lytorch-0.0.4.dist-info/RECORD
