Metadata-Version: 2.1
Name: lytorch
Version: 0.0.4
Summary: my implementation of pytorch
Home-page: https://github.com/luzhixing12345/mytorch
Author: kamilu
Author-email: luzhixing12345@163.com
License: UNKNOWN
Platform: UNKNOWN
Classifier: Programming Language :: Python :: 3
Classifier: License :: OSI Approved :: MIT License
Classifier: Operating System :: OS Independent
License-File: LICENSE
